__init__.py
htls/__init__.py
htls/base_exception.py
htls/cffi_loader.py
htls/cffi/__init__.py
htls/cffi/enums/__init__.py
htls/cffi/enums/client_identifiers.py
htls/cffi/enums/custom_tls_client.py
htls/cffi/funcs/__init__.py
htls/cffi/funcs/cookie.py
htls/cffi/funcs/destroy.py
htls/cffi/funcs/free_memory.py
htls/cffi/funcs/request.py
htls/cffi/objects/__init__.py
htls/cffi/objects/custom_tls_client.py
htls/cffi/objects/request.py
htls/cffi/objects/go/__init__.py
htls/cffi/objects/go/destroy_session_object.py
htls/cffi/objects/go/go_exception.py
htls/cffi/objects/go/go_object.py
htls/cffi/objects/go/response.py
htls/client/__init__.py
htls/client/api.py
htls/client/async_api.py
htls/client/async_session.py
htls/client/auth.py
htls/client/exceptions.py
htls/client/hooks.py
htls/client/prepared_request.py
htls/client/request.py
htls/client/response.py
htls/client/session.py
htls/client/status_codes.py
htls/client/structures.py
htls/client/utils.py
htls/libs/__init__.py
htls/libs/tls-client-darwin-amd64-1.10.0.dylib
htls/libs/tls-client-darwin-arm64-1.10.0.dylib
htls/libs/tls-client-linux-alpine-amd64-1.10.0.so
htls/libs/tls-client-linux-arm64-1.10.0.so
htls/libs/tls-client-linux-ubuntu-amd64-1.10.0.so
htls/libs/tls-client-windows-32-1.10.0.dll
htls/libs/tls-client-windows-64-1.10.0.dll
htls-0.9.1.dist-info/licenses/LICENSE
htls-0.9.1.dist-info/METADATA
htls-0.9.1.dist-info/WHEEL
htls-0.9.1.dist-info/top_level.txt
htls-0.9.1.dist-info/RECORD
