Metadata-Version: 2.4
Name: htls
Version: 0.9.1
Summary: Add your description here
Requires-Python: >=3.10
License-File: LICENSE
Requires-Dist: idna>=3.10
Dynamic: license-file
